ezplock/__init__.py
ezplock-0.0.1.dist-info/METADATA
ezplock-0.0.1.dist-info/WHEEL
ezplock-0.0.1.dist-info/top_level.txt
ezplock-0.0.1.dist-info/RECORD
