Metadata-Version: 2.1
Name: ezplock
Version: 0.0.1
Summary: python code file locker.
Home-page: UNKNOWN
Author: Manav Agarwal
Author-email: manavagarwal.3736@gmail.com
License: UNKNOWN
Keywords: python,file,locker,compiler
Platform: UNKNOWN
Classifier: Development Status :: 1 - Planning
Classifier: Intended Audience :: Developers
Classifier: Programming Language :: Python :: 3
Classifier: Operating System :: Unix
Classifier: Operating System :: MacOS :: MacOS X
Classifier: Operating System :: Microsoft :: Windows
